pyvisonicalarm/__init__.py
pyvisonicalarm/alarm.py
pyvisonicalarm/classes.py
pyvisonicalarm/const.py
pyvisonicalarm/core.py
pyvisonicalarm/device_definitions.py
pyvisonicalarm/devices.py
pyvisonicalarm/exceptions.py
pyvisonicalarm-0.1.0b7.dist-info/LICENSE
pyvisonicalarm-0.1.0b7.dist-info/METADATA
pyvisonicalarm-0.1.0b7.dist-info/WHEEL
pyvisonicalarm-0.1.0b7.dist-info/top_level.txt
pyvisonicalarm-0.1.0b7.dist-info/RECORD
