Metadata-Version: 2.1
Name: pyvisonicalarm
Version: 0.1.0b7
Summary: A simple library for the Visonic Alarm API written in Python 3
Home-page: https://github.com/msp1974/pyvisonicalarm
Author: Mark Parker
Author-email: msparker@sky.com
Classifier: Programming Language :: Python :: 3
Classifier: License :: OSI Approved :: MIT License
Classifier: Operating System :: OS Independent
Requires-Python: >=3.10
License-File: LICENSE
Requires-Dist: requests
